marali_mkdocs_glightbox-0.4.1.dist-info/licenses/LICENSE
mkdocs_glightbox/__init__.py
mkdocs_glightbox/plugin.py
mkdocs_glightbox/glightbox/LICENSE.md
mkdocs_glightbox/glightbox/__init__.py
mkdocs_glightbox/glightbox/glightbox.min.css
mkdocs_glightbox/glightbox/glightbox.min.js
marali_mkdocs_glightbox-0.4.1.dist-info/METADATA
marali_mkdocs_glightbox-0.4.1.dist-info/WHEEL
marali_mkdocs_glightbox-0.4.1.dist-info/entry_points.txt
marali_mkdocs_glightbox-0.4.1.dist-info/top_level.txt
marali_mkdocs_glightbox-0.4.1.dist-info/RECORD
