Metadata-Version: 2.4
Name: marali_mkdocs-glightbox
Version: 0.4.1
Summary: MkDocs plugin supports image lightbox with GLightbox.
Home-page: https://blueswen.github.io/mkdocs-glightbox
Author: Blueswen
Author-email: Blueswen <blueswen.tw@gmail.com>
License: MIT License
Project-URL: Homepage, https://blueswen.github.io/mkdocs-glightbox
Project-URL: Source, https://github.com/Blueswen/mkdocs-glightbox
Keywords: mkdocs,plugin,lightbox
Classifier: Development Status :: 4 - Beta
Classifier: Intended Audience :: Developers
Classifier: License :: OSI Approved :: MIT License
Classifier: Programming Language :: Python
Classifier: Programming Language :: Python :: 3
Classifier: Programming Language :: Python :: 3 :: Only
Classifier: Programming Language :: Python :: 3.8
Classifier: Programming Language :: Python :: 3.9
Classifier: Programming Language :: Python :: 3.10
Classifier: Programming Language :: Python :: 3.11
Classifier: Programming Language :: Python :: 3.12
Classifier: Topic :: Software Development :: Build Tools
Classifier: Topic :: Documentation
Requires-Python: >=3.8
License-File: LICENSE
Requires-Dist: mkdocs>=1.4
Provides-Extra: dev
Requires-Dist: pytest; extra == "dev"
Requires-Dist: pytest-cov; extra == "dev"
Requires-Dist: mkdocs-material; extra == "dev"
Requires-Dist: click; extra == "dev"
Requires-Dist: codecov; python_version < "3.13" and extra == "dev"
Dynamic: author
Dynamic: home-page
Dynamic: license-file
